SnakeScan/CLI.py
SnakeScan/Check_subnet.py
SnakeScan/Get_ssl.py
SnakeScan/__init__.py
snakescan-1.9.1.dist-info/entry_points.txt
snakescan-1.9.1.dist-info/licenses/LICENSE
snakescan-1.9.1.dist-info/WHEEL
snakescan-1.9.1.dist-info/METADATA
snakescan-1.9.1.dist-info/RECORD
