Metadata-Version: 2.4
Name: SnakeScan
Version: 1.9.1
Summary: Unlock the potential of your network with this powerful IPv4 address scanner. Easily scan IP address ranges, identify active hosts, and even extract IPv4 addresses from IPv6 environments. Enhance your network monitoring, troubleshooting, and security analysis!
Author: Den*Ram
Requires-Python: >=3.7
License-Expression: MIT
License-File: LICENSE
Requires-Dist: art
Requires-Dist: tqdm
Requires-Dist: termcolor
